lambda_or/__init__.py
lambda_or/lambda_or.py
lambda_or-0.0.3.dist-info/LICENSE
lambda_or-0.0.3.dist-info/METADATA
lambda_or-0.0.3.dist-info/WHEEL
lambda_or-0.0.3.dist-info/top_level.txt
lambda_or-0.0.3.dist-info/RECORD
