Metadata-Version: 2.1
Name: lambda-or
Version: 0.0.3
Summary: Lambda Odds Ratio
Home-page: https://github.com/zeroknowledgediscovery/lambda_or
Download-URL: https://github.com/zeroknowledgediscovery/lambda_or/archive/0.0.3.tar.gz
Author: Ishanu Chattopadhyay
Author-email: zeroknowledgediscovery@gmail.com
License: LICENSE
Keywords: robust odds ratio,misclassification correction,machine learning,EHR databases
Classifier: Development Status :: 4 - Beta
Classifier: Intended Audience :: Developers
Classifier: Intended Audience :: Science/Research
Classifier: Topic :: Scientific/Engineering :: Information Analysis
Classifier: Topic :: Scientific/Engineering :: Bio-Informatics
Classifier: Topic :: Software Development :: Libraries
Classifier: License :: OSI Approved :: MIT License
Classifier: Programming Language :: Python :: 3.9
Requires-Python: >=3.6
License-File: LICENSE
Requires-Dist: scikit-learn
Requires-Dist: scipy
Requires-Dist: numpy
Requires-Dist: pandas
